api_signature/__init__.py
api_signature-0.0.4.dist-info/WHEEL
api_signature-0.0.4.dist-info/METADATA
api_signature-0.0.4.dist-info/RECORD
