Metadata-Version: 2.3
Name: api-signature
Version: 0.0.4
Summary: 用于生成和验证 HMAC-SHA256 请求签名的工具库
Author: Tenny
Author-email: Tenny <tenny.shu@foxmail.com>
License: MIT License
Classifier: Programming Language :: Python :: 3.11
Classifier: License :: OSI Approved :: MIT License
Classifier: Operating System :: OS Independent
Requires-Python: >=3.11
Project-URL: Bug Tracker, https://github.com/DvShu/api-signature-py/issues
Project-URL: Homepage, https://github.com/DvShu/api-signature-py
